odoo/addons/remove_odoo_mobile_appstore/README.rst
odoo/addons/remove_odoo_mobile_appstore/__init__.py
odoo/addons/remove_odoo_mobile_appstore/__manifest__.py
odoo/addons/remove_odoo_mobile_appstore/i18n/remove_odoo_mobile_appstore.pot
odoo/addons/remove_odoo_mobile_appstore/readme/CONTRIBUTORS.rst
odoo/addons/remove_odoo_mobile_appstore/readme/DESCRIPTION.rst
odoo/addons/remove_odoo_mobile_appstore/static/description/icon.png
odoo/addons/remove_odoo_mobile_appstore/static/description/index.html
odoo/addons/remove_odoo_mobile_appstore/tests/__init__.py
odoo/addons/remove_odoo_mobile_appstore/tests/test_remove_odoo_appstore.py
odoo/addons/remove_odoo_mobile_appstore/views/res_config_settings_views.xml
odoo13_addon_remove_odoo_mobile_appstore-13.0.1.0.1.dev3.dist-info/METADATA
odoo13_addon_remove_odoo_mobile_appstore-13.0.1.0.1.dev3.dist-info/WHEEL
odoo13_addon_remove_odoo_mobile_appstore-13.0.1.0.1.dev3.dist-info/top_level.txt
odoo13_addon_remove_odoo_mobile_appstore-13.0.1.0.1.dev3.dist-info/RECORD
